constants/__init__.py
constants/constants.py
JScyPi-0.1.1.dist-info/LICENSE.txt
JScyPi-0.1.1.dist-info/METADATA
JScyPi-0.1.1.dist-info/WHEEL
JScyPi-0.1.1.dist-info/top_level.txt
JScyPi-0.1.1.dist-info/RECORD
