Metadata-Version: 2.1
Name: JScyPi
Version: 0.1.1
Summary: Mathematical and Scientific Constants and methods
Author: Jonios
Author-email: giannisvar2015@gmail.com
Classifier: Programming Language :: Python :: 3
Classifier: License :: OSI Approved :: MIT License
Classifier: Operating System :: OS Independent
Requires-Python: >=3.6
License-File: LICENSE.txt
